themule/VERSION
themule/__init__.py
themule/__main__.py
themule/backends.py
themule/cli.py
themule/conf.py
themule/decorators.py
themule/exceptions.py
themule/executor.py
themule/import_helpers.py
themule/job.py
themule/serializers.py
themule-0.3.0.dist-info/METADATA
themule-0.3.0.dist-info/WHEEL
themule-0.3.0.dist-info/entry_points.txt
themule-0.3.0.dist-info/top_level.txt
themule-0.3.0.dist-info/RECORD
