Metadata-Version: 2.1
Name: themule
Version: 0.3.0
Summary: The Mule - run arbitrary python function on AWS Batch
Home-page: http://github.com/wlatanowicz/themule
Author: Wiktor Latanowicz
Author-email: wiktor@latanowicz.com
License: MIT
Classifier: Programming Language :: Python :: 3.9
Classifier: License :: OSI Approved :: MIT License
Classifier: Operating System :: OS Independent
Requires-Python: >=3.9
Requires-Dist: click >=8.1.3
Requires-Dist: django-environ >=0.9.0
Provides-Extra: aws_batch
Requires-Dist: boto3 >=1.23.5 ; extra == 'aws_batch'
Provides-Extra: docker
Requires-Dist: docker >=6.1.3 ; extra == 'docker'
Provides-Extra: redis
Requires-Dist: redis ; extra == 'redis'
